Fighting_Plane/__init__.py
Fighting_Plane/bullet.py
Fighting_Plane/enemy.py
Fighting_Plane/main.py
Fighting_Plane/myplane.py
Fighting_Plane/record.txt
Fighting_Plane/supply.py
Fighting_Plane/font/font.ttf
Fighting_Plane/images/again.png
Fighting_Plane/images/background.png
Fighting_Plane/images/bomb.png
Fighting_Plane/images/bomb_supply.png
Fighting_Plane/images/bullet1.png
Fighting_Plane/images/bullet2.png
Fighting_Plane/images/bullet_supply.png
Fighting_Plane/images/enemy1.png
Fighting_Plane/images/enemy1_down1.png
Fighting_Plane/images/enemy1_down2.png
Fighting_Plane/images/enemy1_down3.png
Fighting_Plane/images/enemy1_down4.png
Fighting_Plane/images/enemy2.png
Fighting_Plane/images/enemy2_down1.png
Fighting_Plane/images/enemy2_down2.png
Fighting_Plane/images/enemy2_down3.png
Fighting_Plane/images/enemy2_down4.png
Fighting_Plane/images/enemy2_hit.png
Fighting_Plane/images/enemy3_down1.png
Fighting_Plane/images/enemy3_down2.png
Fighting_Plane/images/enemy3_down3.png
Fighting_Plane/images/enemy3_down4.png
Fighting_Plane/images/enemy3_down5.png
Fighting_Plane/images/enemy3_down6.png
Fighting_Plane/images/enemy3_hit.png
Fighting_Plane/images/enemy3_n1.png
Fighting_Plane/images/enemy3_n2.png
Fighting_Plane/images/gameover.png
Fighting_Plane/images/life.png
Fighting_Plane/images/me1.png
Fighting_Plane/images/me2.png
Fighting_Plane/images/me_destroy_1.png
Fighting_Plane/images/me_destroy_2.png
Fighting_Plane/images/me_destroy_3.png
Fighting_Plane/images/me_destroy_4.png
Fighting_Plane/images/pause_nor.png
Fighting_Plane/images/pause_pressed.png
Fighting_Plane/images/resume_nor.png
Fighting_Plane/images/resume_pressed.png
Fighting_Plane/sound/bullet.wav
Fighting_Plane/sound/button.wav
Fighting_Plane/sound/enemy1_down.wav
Fighting_Plane/sound/enemy2_down.wav
Fighting_Plane/sound/enemy3_down.wav
Fighting_Plane/sound/enemy3_flying.wav
Fighting_Plane/sound/game_music.ogg
Fighting_Plane/sound/get_bomb.wav
Fighting_Plane/sound/get_bullet.wav
Fighting_Plane/sound/me_down.wav
Fighting_Plane-2024.2.19.dist-info/METADATA
Fighting_Plane-2024.2.19.dist-info/WHEEL
Fighting_Plane-2024.2.19.dist-info/top_level.txt
Fighting_Plane-2024.2.19.dist-info/RECORD
